_pybind_sandbox.cpython-312-darwin.so
pybind_sandbox/__init__.py
pybind_sandbox/__init__.pyi
pybind_sandbox-0.0.1.dist-info/METADATA
pybind_sandbox-0.0.1.dist-info/WHEEL
pybind_sandbox-0.0.1.dist-info/top_level.txt
pybind_sandbox-0.0.1.dist-info/RECORD
