Metadata-Version: 2.1
Name: pybind_sandbox
Version: 0.0.1
Summary: Python interface to PartMC
Author: PyPartMC team (see https://github.com/open-atmos/PyPartMC/graphs/contributors)
Author-email: nriemer@illinois.edu
License: GPL-3.0
Requires-Python: >=3.7
Requires-Dist: numpy
